es_client/__init__.py
es_client/builder.py
es_client/cli_example.py
es_client/commands.py
es_client/config.py
es_client/debug.py
es_client/defaults.py
es_client/exceptions.py
es_client/logging.py
es_client/py.typed
es_client/schemacheck.py
es_client/utils.py
es_client-9.0.1.dist-info/METADATA
es_client-9.0.1.dist-info/WHEEL
es_client-9.0.1.dist-info/licenses/LICENSE
es_client-9.0.1.dist-info/RECORD
