Metadata-Version: 2.3
Name: es_client
Version: 9.0.1
Summary: Elasticsearch Client builder, complete with schema validation
Project-URL: Homepage, https://github.com/untergeek/es_client
Project-URL: Bug Tracker, https://github.com/untergeek/es_client/issues
Project-URL: Documentation, https://es-client.readthedocs.io/
Project-URL: Source Code, http://github.com/untergeek/es_client
Project-URL: Release Notes, https://github.com/untergeek/es_client/releases
Author-email: Aaron Mildenstein <aaron@mildensteins.com>
License: Apache-2.0
License-File: LICENSE
Keywords: client,command-line,connect,elasticsearch
Classifier: Intended Audience :: Developers
Classifier: License :: OSI Approved :: Apache Software License
Classifier: Operating System :: OS Independent
Classifier: Programming Language :: Python :: 3.10
Classifier: Programming Language :: Python :: 3.11
Classifier: Programming Language :: Python :: 3.12
Classifier: Programming Language :: Python :: 3.13
Requires-Python: >=3.10
Requires-Dist: certifi>=2025.8.3
Requires-Dist: click==8.3.0
Requires-Dist: cryptography>=44.0.2
Requires-Dist: dotmap==1.3.30
Requires-Dist: ecs-logging==2.2.0
Requires-Dist: elasticsearch9==9.1.1
Requires-Dist: pyyaml==6.0.2
Requires-Dist: tiered-debug>=1.3.1
Requires-Dist: voluptuous>=0.14.2
Provides-Extra: doc
Requires-Dist: furo>=2024.8.6; extra == 'doc'
Provides-Extra: test
Requires-Dist: pytest-cov; extra == 'test'
Requires-Dist: pytest-dotenv; extra == 'test'
Requires-Dist: pytest>=7.2.1; extra == 'test'
Requires-Dist: requests; extra == 'test'
